Zones_EA/Telegram.py
Zones_EA/__init__.py
Zones_EA/clustering_catboost.py
Zones_EA/copyFactory.py
Zones_EA/db.py
Zones_EA/logger.py
Zones_EA/manage.py
Zones_EA/models.py
Zones_EA/test.py
Zones_EA/zmq_connector.py
Zones_EA-0.0.1.dist-info/LICENSE.md
Zones_EA-0.0.1.dist-info/METADATA
Zones_EA-0.0.1.dist-info/WHEEL
Zones_EA-0.0.1.dist-info/top_level.txt
Zones_EA-0.0.1.dist-info/RECORD
