Metadata-Version: 2.1
Name: Zones-EA
Version: 0.0.1
License: https://github.com/nguemechieu/Zones_EA/src/docs/license.txt
Classifier: Programming Language :: Python :: 3
Classifier: License :: OSI Approved :: MIT License
Classifier: Operating System :: OS Independent
License-File: LICENSE.md
Requires-Dist: requirements.txt
